multimds/__init__.py
multimds/array_tools.py
multimds/compartment_analysis.py
multimds/compartment_fraction.py
multimds/data_tools.py
multimds/hic_oe.py
multimds/joint_mds.py
multimds/linear_algebra.py
multimds/multimds.py
multimds/plotting.py
multimds/reproducibility.py
multimds/tad.py
multimds/tools.py
multimds-0.0.9.dist-info/DESCRIPTION.rst
multimds-0.0.9.dist-info/METADATA
multimds-0.0.9.dist-info/RECORD
multimds-0.0.9.dist-info/WHEEL
multimds-0.0.9.dist-info/metadata.json
multimds-0.0.9.dist-info/top_level.txt
