Metadata-Version: 2.0
Name: multimds
Version: 0.0.9
Summary: Structural inference and alignment of Hi-C datasets
Home-page: https://github.com/seqcode/multimds
Author: Lila Rieber
Author-email: lr65358@gmail.com
License: UNKNOWN
Platform: UNKNOWN
Classifier: Programming Language :: Python :: 3
Classifier: License :: OSI Approved :: MIT License
Classifier: Operating System :: OS Independent
Requires-Dist: h5py
Requires-Dist: numpy
Requires-Dist: pandas
Requires-Dist: pymp-pypi
Requires-Dist: scikit-learn
Requires-Dist: scipy
Requires-Dist: seaborn
